typedjson/__init__.py
typedjson/annotation.py
typedjson/decoding.py
typedjson/dumping.py
typedjson/loading.py
typedjson/py.typed
typedjson-0.10.4.dist-info/LICENSE
typedjson-0.10.4.dist-info/WHEEL
typedjson-0.10.4.dist-info/METADATA
typedjson-0.10.4.dist-info/RECORD
