Metadata-Version: 2.1
Name: typedjson
Version: 0.10.4
Summary: JSON decoding for Python with type hinting (PEP 484)
License: MIT
Author: Tomoya Kose
Author-email: tomoya@mitsuse.jp
Requires-Python: >=3.6,<4.0
Classifier: Development Status :: 1 - Planning
Classifier: License :: OSI Approved :: MIT License
Classifier: Programming Language :: Python :: 3
Classifier: Programming Language :: Python :: 3.6
Classifier: Programming Language :: Python :: 3.7
Classifier: Programming Language :: Python :: 3.8
Classifier: Programming Language :: Python :: 3.9
Requires-Dist: dataclasses (>=0.6.0,<0.7.0); python_version < "3.7"
Requires-Dist: typing-extensions (>=3.7,<4.0)
